{"documents": [["my", "printer", "is", "not", "working"], ["printer", "wont", "print"], ["printer", "says", "offline"], ["paper", "jam", "in", "printer"], ["printer", "out", "of", "ink"], ["cant", "print", "document"], ["print", "job", "stuck"], ["forgot", "my", "password"], ["cant", "login", "to", "account"], ["reset", "my", "password"], ["password", "not", "working"], ["account", "locked", "out"], ["login", "failed"], ["wifi", "not", "connecting"], ["internet", "is", "down"], ["no", "internet", "connection"], ["wifi", "keeps", "disconnecting"], ["cant", "connect", "to", "wifi"], ["ethernet", "not", "working"], ["computer", "is", "slow"], ["slow", "performance"], ["computer", "freezing"], ["high", "cpu", "usage"], ["outlook", "not", "opening"], ["excel", "keeps", "crashing"], ["word", "not", "saving"], ["app", "not", "responding"], ["email", "not", "sending"], ["outlook", "not", "syncing"], ["cannot", "receive", "emails"], ["monitor", "not", "turning", "on"], ["computer", "wont", "start"], ["blue", "screen", "error"], ["vpn", "not", "connecting"], ["vpn", "connection", "failed"], ["talk", "to", "a", "human"], ["speak", "to", "an", "agent"]], "categories": ["printer", "printer", "printer", "printer", "printer", "printer", "printer", "password", "password", "password", "password", "password", "password", "network", "network", "network", "network", "network", "network", "performance", "performance", "performance", "performance", "software", "software", "software", "software", "email", "email", "email", "hardware", "hardware", "hardware", "vpn", "vpn", "escalation", "escalation"], "idf": {"working": 2.224623551524334, "not": 1.1260112628562242, "printer": 1.8191584434161694, "is": 2.224623551524334, "my": 2.224623551524334, "print": 2.224623551524334, "wont": 2.512305623976115, "offline": 2.917770732084279, "says": 2.917770732084279, "jam": 2.917770732084279, "in": 2.917770732084279, "paper": 2.917770732084279, "ink": 2.917770732084279, "of": 2.917770732084279, "out": 2.512305623976115, "document": 2.917770732084279, "cant": 2.224623551524334, "stuck": 2.917770732084279, "job": 2.917770732084279, "forgot": 2.917770732084279, "password": 2.224623551524334, "login": 2.512305623976115, "to": 2.0014800002101243, "account": 2.512305623976115, "reset": 2.917770732084279, "locked": 2.917770732084279, "failed": 2.512305623976115, "connecting": 2.512305623976115, "wifi": 2.224623551524334, "internet": 2.512305623976115, "down": 2.917770732084279, "no": 2.917770732084279, "connection": 2.512305623976115, "disconnecting": 2.917770732084279, "keeps": 2.512305623976115, "connect": 2.917770732084279, "ethernet": 2.917770732084279, "computer": 2.224623551524334, "slow": 2.512305623976115, "performance": 2.917770732084279, "freezing": 2.917770732084279, "cpu": 2.917770732084279, "high": 2.917770732084279, "usage": 2.917770732084279, "opening": 2.917770732084279, "outlook": 2.512305623976115, "crashing": 2.917770732084279, "excel": 2.917770732084279, "saving": 2.917770732084279, "word": 2.917770732084279, "responding": 2.917770732084279, "app": 2.917770732084279, "sending": 2.917770732084279, "email": 2.917770732084279, "syncing": 2.917770732084279, "cannot": 2.917770732084279, "receive": 2.917770732084279, "emails": 2.917770732084279, "on": 2.917770732084279, "turning": 2.917770732084279, "monitor": 2.917770732084279, "start": 2.917770732084279, "error": 2.917770732084279, "blue": 2.917770732084279, "screen": 2.917770732084279, "vpn": 2.512305623976115, "a": 2.917770732084279, "human": 2.917770732084279, "talk": 2.917770732084279, "speak": 2.917770732084279, "an": 2.917770732084279, "agent": 2.917770732084279}, "vocabulary": {"not": 0, "forgot": 1, "printer": 2, "outlook": 3, "talk": 4, "usage": 5, "saving": 6, "sending": 7, "connection": 8, "ink": 9, "my": 10, "error": 11, "vpn": 12, "word": 13, "paper": 14, "connect": 15, "excel": 16, "monitor": 17, "start": 18, "cpu": 19, "internet": 20, "ethernet": 21, "to": 22, "failed": 23, "cannot": 24, "screen": 25, "human": 26, "freezing": 27, "emails": 28, "an": 29, "out": 30, "stuck": 31, "wifi": 32, "down": 33, "no": 34, "in": 35, "slow": 36, "of": 37, "agent": 38, "working": 39, "password": 40, "email": 41, "connecting": 42, "wont": 43, "receive": 44, "document": 45, "account": 46, "cant": 47, "performance": 48, "keeps": 49, "computer": 50, "high": 51, "jam": 52, "blue": 53, "locked": 54, "offline": 55, "speak": 56, "crashing": 57, "responding": 58, "says": 59, "disconnecting": 60, "on": 61, "opening": 62, "syncing": 63, "turning": 64, "is": 65, "a": 66, "reset": 67, "job": 68, "print": 69, "login": 70, "app": 71}}